wormpix/__init__.py
wormpix/wormpix.py
wormpix/wormpix_icon.png
wormpix-1.2.0.dist-info/licenses/LICENSE
wormpix-1.2.0.dist-info/METADATA
wormpix-1.2.0.dist-info/WHEEL
wormpix-1.2.0.dist-info/entry_points.txt
wormpix-1.2.0.dist-info/top_level.txt
wormpix-1.2.0.dist-info/RECORD
