Metadata-Version: 2.4
Name: wormpix
Version: 1.2.0
Summary: 🐉 WormPix - Advanced Eye Comfort & Screen Warmth Tool with Eye Rest Alarm
Home-page: https://github.com/LunarLumos/wormpix
Author: Lunar Labs
Author-email: aadil025@yahoo.com
Classifier: Programming Language :: Python :: 3
Classifier: Operating System :: POSIX :: Linux
Classifier: Topic :: Desktop Environment
Requires-Python: >=3.7
License-File: LICENSE
Requires-Dist: PyQt6
Dynamic: author
Dynamic: author-email
Dynamic: classifier
Dynamic: home-page
Dynamic: license-file
Dynamic: requires-dist
Dynamic: requires-python
Dynamic: summary
